{
  "project_info": {
    "project_number": "725592645188",
    "project_id": "knowitall-admin",
    "storage_bucket": "knowitall-admin.appspot.com"
  },
  "client": [
    {
      "client_info": {
        "mobilesdk_app_id": "1:725592645188:android:dd24b654a1296f83ffe611",
        "android_client_info": {
          "package_name": "com.example.knowitall"
        }
      },
      "oauth_client": [],
      "api_key": [
        {
          "current_key": "AIzaSyCPJgXjZcDYI_8qewWvX1_LtPA9-GgSo-4"
        }
      ],
      "services": {
        "appinvite_service": {
          "other_platform_oauth_client": []
        }
      }
    }
  ],
  "configuration_version": "1"
}